dj_emailauth/__init__.py
dj_emailauth/apps.py
dj_emailauth/migrations/0001_initial.py
dj_emailauth/migrations/__init__.py
dj_emailauth/models.py
dj_emailauth-0.2.0.dist-info/LICENSE
dj_emailauth-0.2.0.dist-info/WHEEL
dj_emailauth-0.2.0.dist-info/METADATA
dj_emailauth-0.2.0.dist-info/RECORD
