Metadata-Version: 2.1
Name: dj-emailauth
Version: 0.2.0
Summary: 
Author: Martin Hloska
Author-email: martin.hloska@gmail.com
Requires-Python: >=3.9,<4.0
Classifier: Programming Language :: Python :: 3
Classifier: Programming Language :: Python :: 3.9
Requires-Dist: Django (>=3.0,<4.0)
